projectdump/__init__.py
projectdump/__main__.py
projectdump/aggregator.py
projectdump/constants.py
projectdump/detector.py
projectdump/filters.py
projectdump/one_file_version.py
projectdump/tree_generator.py
projectdump-0.1.0.dist-info/licenses/LICENSE
projectdump-0.1.0.dist-info/METADATA
projectdump-0.1.0.dist-info/WHEEL
projectdump-0.1.0.dist-info/entry_points.txt
projectdump-0.1.0.dist-info/top_level.txt
projectdump-0.1.0.dist-info/RECORD
