Metadata-Version: 2.4
Name: projectdump
Version: 0.1.0
Summary: Generate full source dump summary for any project
Author-email: Nguyễn Huỳnh Anh Khoa <you@example.com>, Nguyen Huy <ntqhuy2k2@gmail.com>
License: MIT License
Requires-Python: >=3.8
License-File: LICENSE
Dynamic: license-file
